{
    "object" : {

	"childs" : [
	],

	"components" : [
	    {
		"type" : "ctvty::component::Camera",
		"object" : {
		    "viewport id" : 1,
		    "locked look" : {
			"object" : {
			    "x" : 0,
			    "y" : 10,
			    "z" : 0,
			},
			"type" : "ctvty::utils::Vector3D",
		    },
		    "tilt" : 0,
		}
	    },
	],

	"name" : "template GameObject"
	"tag" : "undefined"

	"transform" : {
	    "object" : {
		"position" : {
		    "object" : {
			"x" : -20,
			"y" : 20,
			"z" : 0,
		    },
		    "type" : "ctvty::utils::Vector3D",
		},
		"rotation" : {
		    "object" : {
			"x" : 0,
			"y" : 0,
			"z" : 0,
			"w" : 0
		    },
		    "type" : "ctvty::utils::Quaternion",
		},
		"scale" : {
		    "object" : {
			"x" : 1,
			"y" : 1,
			"z" : 1,
		    },
		    "type" : "ctvty::utils::Vector3D",
		},
	    },
	    "type" : "ctvty::component::Transform",
	}
    },
    "type" : "ctvty::GameObject"
}
